canvas_db/__init__.py
canvas_db/config.py
canvas_db/models.py
canvas_db/orm.py
python_canvas-0.1.9.dist-info/LICENSE
python_canvas-0.1.9.dist-info/METADATA
python_canvas-0.1.9.dist-info/WHEEL
python_canvas-0.1.9.dist-info/top_level.txt
python_canvas-0.1.9.dist-info/RECORD
