Metadata-Version: 2.1
Name: python-canvas
Version: 0.1.9
Summary: Данная библиотека содержить SqlAlchemy ORM для системы Canvas
Home-page: https://github.com/yessenovuniversity/python_canvas
Author: Nauryzbek Aitbayev
Author-email: nauryzbek.aitbayev@yu.edu.kz
License: UNKNOWN
Platform: UNKNOWN
Classifier: Programming Language :: Python :: 3
Classifier: License :: Other/Proprietary License
Classifier: Operating System :: OS Independent
Requires-Python: >=3.6
Requires-Dist: sqlalchemy
Requires-Dist: psycopg2
